cfspider/__init__.py
cfspider/api.py
cfspider/async_api.py
cfspider/async_session.py
cfspider/batch.py
cfspider/browser.py
cfspider/cli.py
cfspider/export.py
cfspider/extract.py
cfspider/impersonate.py
cfspider/ip_map.py
cfspider/mirror.py
cfspider/proxy_server.py
cfspider/session.py
cfspider/stealth.py
cfspider/vless_client.py
cfspider/workers_manager.py
cfspider/data/__init__.py
cfspider/data/dataframe.py
cfspider/data/io.py
cfspider/workers/vless_workers.js
cfspider/workers/workers.js
cfspider/workers/爬楼梯workers.js
cfspider/workers/破皮版workers.js
cfspider/workers/破皮版workers_明文.js
cfspider/workers/破皮版workers_超明文.js
cfspider/x27cn/__init__.py
cfspider/x27cn/__main__.py
cfspider/x27cn/name_gen.py
cfspider/x27cn/obfuscator.py
cfspider/x27cn/string_crypt.py
cfspider-1.9.0.dist-info/licenses/LICENSE
cfspider-video/node_modules/flatted/python/flatted.py
cfspider-1.9.0.dist-info/METADATA
cfspider-1.9.0.dist-info/WHEEL
cfspider-1.9.0.dist-info/entry_points.txt
cfspider-1.9.0.dist-info/top_level.txt
cfspider-1.9.0.dist-info/RECORD
