Metadata-Version: 2.4
Name: cfspider
Version: 1.9.0
Summary: Cloudflare Workers proxy IP pool client
Author-email: violettools <violet@violetteam.cloud>
License: Apache-2.0
Project-URL: Homepage, https://cfspider.com
Project-URL: Repository, https://github.com/violettoolssite/CFspider
Keywords: cloudflare,workers,proxy,spider,scraper,crawler
Classifier: Development Status :: 4 - Beta
Classifier: License :: OSI Approved :: Apache Software License
Classifier: Programming Language :: Python :: 3
Requires-Python: >=3.8
License-File: LICENSE
Requires-Dist: requests>=2.20.0
Requires-Dist: httpx[http2]>=0.25.0
Requires-Dist: curl_cffi>=0.5.0
Requires-Dist: beautifulsoup4>=4.9.0
Requires-Dist: playwright>=1.40.0
Requires-Dist: lxml>=4.9.0
Requires-Dist: jsonpath-ng>=1.5.0
Requires-Dist: openpyxl>=3.0.0
Requires-Dist: tqdm>=4.60.0
Provides-Extra: browser
Requires-Dist: playwright>=1.40.0; extra == "browser"
Provides-Extra: xpath
Requires-Dist: lxml>=4.9.0; extra == "xpath"
Provides-Extra: jsonpath
Requires-Dist: jsonpath-ng>=1.5.0; extra == "jsonpath"
Provides-Extra: excel
Requires-Dist: openpyxl>=3.0.0; extra == "excel"
Provides-Extra: progress
Requires-Dist: tqdm>=4.60.0; extra == "progress"
Provides-Extra: extract
Requires-Dist: lxml>=4.9.0; extra == "extract"
Requires-Dist: jsonpath-ng>=1.5.0; extra == "extract"
Requires-Dist: openpyxl>=3.0.0; extra == "extract"
Requires-Dist: tqdm>=4.60.0; extra == "extract"
Provides-Extra: all
Requires-Dist: playwright>=1.40.0; extra == "all"
Requires-Dist: lxml>=4.9.0; extra == "all"
Requires-Dist: jsonpath-ng>=1.5.0; extra == "all"
Requires-Dist: openpyxl>=3.0.0; extra == "all"
Requires-Dist: tqdm>=4.60.0; extra == "all"
Dynamic: license-file
